mgwr/__init__.py
mgwr/diagnostics.py
mgwr/gwr.py
mgwr/kernels.py
mgwr/search.py
mgwr/sel_bw.py
mgwr/summary.py
mgwr/utils.py
mgwr/tests/__init__.py
mgwr/tests/test_gwr.py
mgwr/tests/test_kernels.py
mgwr/tests/test_parallel.py
mgwr/tests/test_sel_bw.py
mgwr-2.2.1.dist-info/LICENSE
mgwr-2.2.1.dist-info/METADATA
mgwr-2.2.1.dist-info/WHEEL
mgwr-2.2.1.dist-info/top_level.txt
mgwr-2.2.1.dist-info/RECORD
